databroker/__init__.py
databroker/_core.py
databroker/_legacy_images.py
databroker/_version.py
databroker/broker.py
databroker/core.py
databroker/databroker.py
databroker/discovery.py
databroker/glue.py
databroker/in_memory.py
databroker/pims_readers.py
databroker/pivot.py
databroker/projector.py
databroker/queries.py
databroker/tutorial_utils.py
databroker/utils.py
databroker/v0.py
databroker/v1.py
databroker/v2.py
databroker/_drivers/__init__.py
databroker/_drivers/jsonl.py
databroker/_drivers/mongo_embedded.py
databroker/_drivers/mongo_normalized.py
databroker/_drivers/msgpack.py
databroker/assets/__init__.py
databroker/assets/base_registry.py
databroker/assets/column_hdf5.py
databroker/assets/core.py
databroker/assets/file_writers.py
databroker/assets/handlers.py
databroker/assets/handlers_base.py
databroker/assets/mongo.py
databroker/assets/mongo_core.py
databroker/assets/path_only_handlers.py
databroker/assets/sqlite.py
databroker/assets/utils.py
databroker/assets/readers/__init__.py
databroker/assets/readers/spe.py
databroker/assets/schemas/AD_HDF5_datum.json
databroker/assets/schemas/AD_HDF5_resource.json
databroker/assets/schemas/AD_SPE_datum.json
databroker/assets/schemas/AD_SPE_resource.json
databroker/assets/tests/__init__.py
databroker/assets/tests/conftest.py
databroker/assets/tests/test_asset.py
databroker/assets/tests/test_fs.py
databroker/assets/tests/test_fs_mutate.py
databroker/assets/tests/test_handlers.py
databroker/assets/tests/test_mongo_details.py
databroker/assets/tests/test_reader.py
databroker/assets/tests/test_retrieve.py
databroker/assets/tests/test_write.py
databroker/assets/tests/utils.py
databroker/eventsource/__init__.py
databroker/eventsource/archiver.py
databroker/eventsource/shim.py
databroker/eventsource/tests/__init__.py
databroker/eventsource/tests/test_archiver.py
databroker/eventsource/tests/test_broker.py
databroker/eventsource/tests/test_shim.py
databroker/eventsource/tests/utils.py
databroker/headersource/__init__.py
databroker-1.2.5.dist-info/LICENSE
databroker-1.2.5.dist-info/METADATA
databroker-1.2.5.dist-info/WHEEL
databroker-1.2.5.dist-info/entry_points.txt
databroker-1.2.5.dist-info/top_level.txt
databroker-1.2.5.dist-info/RECORD
