Metadata-Version: 2.1
Name: databroker
Version: 1.2.5
Summary: Unification of NSLS-II data sources
Home-page: https://github.com/NSLS-II/databroker
Author: Brookhaven National Laboratory
License: BSD (3-clause)
Platform: UNKNOWN
Classifier: License :: OSI Approved :: BSD License
Classifier: Development Status :: 4 - Beta
Classifier: Programming Language :: Python :: 2
Classifier: Programming Language :: Python :: 2.7
Classifier: Programming Language :: Python :: 3
Classifier: Programming Language :: Python :: 3.4
Classifier: Programming Language :: Python :: 3.5
Classifier: Programming Language :: Python :: 3.6
Requires-Python: >=3.6
Provides-Extra: mongo
Provides-Extra: hdf5
Provides-Extra: client
Provides-Extra: service
Provides-Extra: all
License-File: LICENSE
